LICENSE
setup.py
ugle/__init__.py
ugle/datasets.py
ugle/gnn_architecture.py
ugle/hpo.py
ugle/logger.py
ugle/process.py
ugle/trainer.py
ugle/utils.py
ugle.egg-info/PKG-INFO
ugle.egg-info/SOURCES.txt
ugle.egg-info/dependency_links.txt
ugle.egg-info/requires.txt
ugle.egg-info/top_level.txt
ugle/models/__init__.py
ugle/models/bgrl.py
ugle/models/cagc.py
ugle/models/daegc.py
ugle/models/dgi.py
ugle/models/dmon.py
ugle/models/grace.py
ugle/models/mvgrl.py
ugle/models/selfgnn.py
ugle/models/sublime.py
ugle/models/vgaer.py