Metadata-Version: 2.1
Name: ugle
Version: 0.6.0
Summary: This is a repository for investigating implementations of GNNs for                    unsupervised clustering.
Home-page: https://github.com/willleeney/ugle
Author: William Leeney
Author-email: will.leeney@outlook.com
Classifier: Development Status :: 4 - Beta
Classifier: Intended Audience :: Science/Research
Classifier:  Intended Audience :: Information Technology
Classifier: Operating System :: POSIX :: Linux
Classifier: Programming Language :: Python :: 3.9
Requires-Python: >=3.9.12
License-File: LICENSE
